CSVAlchemy/__init__.py
CSVAlchemy/main.py
CSVAlchemy/config/__init__.py
CSVAlchemy/config/default_config.py
CSVAlchemy/core/__init__.py
CSVAlchemy/core/spreadsheet_parser.py
CSVAlchemy/utils/__init__.py
CSVAlchemy/utils/excel.py
csvalchemy_sdk-0.1.3.dist-info/licenses/LICENSE
csvalchemy_sdk-0.1.3.dist-info/METADATA
csvalchemy_sdk-0.1.3.dist-info/WHEEL
csvalchemy_sdk-0.1.3.dist-info/top_level.txt
csvalchemy_sdk-0.1.3.dist-info/RECORD
