Metadata-Version: 2.4
Name: CSVAlchemy_sdk
Version: 0.1.3
Summary: A lightweight Python client SDK for the CSValchemy API
Home-page: https://github.com/Unsiloed-AI/csvalchemy-sdk
Author: Unsiloed.Ai
Author-email: Your Name <your@email.com>
License: MIT
Requires-Python: >=3.9
License-File: LICENSE
Requires-Dist: requests>=2.25
Dynamic: author
Dynamic: home-page
Dynamic: license-file
Dynamic: requires-python
